src/alu.v
/*
ALU Supported Operations:   
--------------------------------
000: Add
001: Sub
010: AND (bitwise)
011: OR (bitwise)
100: XOR (bitwise)
101: SLL (Logical shift left, <<)
110: SRL (Logical shift right, >>)
111: Set on less than
*/

/*
To do:
    - Expand supported operations (i.e. make op to 4 bits)
    - Add more flags to support branching (i.e. carry, negative, overflow, parity)
*/

module ALU (
    input[31:0] a, b,
    input[2:0] op,
    output reg[31:0] result,
    output reg zeroFlag
);

always @(*) begin

    case(op)
        3'b000: result = a + b;
        3'b001: result = a - b;
        3'b010: result = a & b;
        3'b011: result = a | b;
        3'b100: result = a ^ b;
        3'b101: result = a << b;
        3'b110: result = a >> b;
        3'b111: begin
            if(a < b) begin
                result = 1;
            end else begin
                result = 0; 
            end
        end
    endcase

    if(result == 0) begin
        zeroFlag = 1;
    end else begin
        zeroFlag = 0;
    end

end

endmodule

tests/alu_test.v
`include "src/alu.v"
`timescale 1ns/1ns

module alu_test();
reg[31:0] a, b;
reg[2:0] op;
wire[31:0] result;
wire zeroFlag;

ALU UUT(a, b, op, result, zeroFlag);

initial begin
    $dumpfile("alu_test.vcd");
    $dumpvars(0, alu_test);

    // add
    a = 32'd5;
    b = 32'd10;
    op = 3'b000;
    #10;

    // sub
    a = 32'd10;
    b = 32'd5;
    op = 3'b001;
    #10;

    // and
    a = 32'd5; // 0...0101
    b = 32'd3; // 0...0011
    op = 3'b010; // Expected result: 0...0001
    #10;

    // or
    a = 32'd5;  
    b = 32'd3;
    op = 3'b011; // Expected result: 0...0111
    #10;

    // xor
    a = 32'd5;
    b = 32'd3;
    op = 3'b100; // Expected result: 0...0110
    #10;

    // SLL
    a = 32'd5;
    b = 32'd2;
    op = 3'b110; // Expected result: 0...10100
    #10;

    // SRL
    a = 32'd4;
    b = 32'd2;
    op = 3'b111; // Expected result: 0...001
    #10;

    // zero
    a = 32'd0;
    b = 32'd0;
    op = 3'b000;
    #10;

    $display("End of test");
end

endmodule

tests/alu_test.vcd
$date
	Fri Jun 06 19:45:21 2025
$end
$version
	Icarus Verilog
$end
$timescale
	1ns
$end
$scope module alu_test $end
$var wire 1 ! zeroFlag $end
$var wire 32 " result [31:0] $end
$var reg 32 # a [31:0] $end
$var reg 32 $ b [31:0] $end
$var reg 3 % op [2:0] $end
$scope module UUT $end
$var wire 32 & a [31:0] $end
$var wire 32 ' b [31:0] $end
$var wire 3 ( op [2:0] $end
$var reg 32 ) result [31:0] $end
$var reg 1 ! zeroFlag $end
$upscope $end
$upscope $end
$enddefinitions $end
$comment Show the parameter values. $end
$dumpall
$end
#0
$dumpvars
b1111 )
b0 (
b1010 '
b101 &
b0 %
b1010 $
b101 #
b1111 "
0!
$end
#10
b101 "
b101 )
b1 %
b1 (
b101 $
b101 '
b1010 #
b1010 &
#20
b1 "
b1 )
b10 %
b10 (
b11 $
b11 '
b101 #
b101 &
#30
b111 "
b111 )
b11 %
b11 (
#40
b110 "
b110 )
b100 %
b100 (
#50
b1 "
b1 )
b110 %
b110 (
b10 $
b10 '
#60
1!
b0 "
b0 )
b111 %
b111 (
b100 #
b100 &
#70
b0 %
b0 (
b0 $
b0 '
b0 #
b0 &
